autora/experimentalist/pooler/poppernet.py
autora_experimentalist_poppernet-1.0.0a0.dist-info/METADATA
autora_experimentalist_poppernet-1.0.0a0.dist-info/WHEEL
autora_experimentalist_poppernet-1.0.0a0.dist-info/top_level.txt
autora_experimentalist_poppernet-1.0.0a0.dist-info/RECORD
