Metadata-Version: 2.1
Name: autora-experimentalist-poppernet
Version: 1.0.0a0
Summary: Pooler that generates samples for independent variables by maximizing the loss
Author-email: Sebastian Musslick <sebastian_musslick@brown.edu>
License: MIT License
Project-URL: homepage, http://www.empiricalresearch.ai
Project-URL: repository, https://github.com/AutoResearch/autora-experimentalist-poppernet
Project-URL: documentation, https://autoresearch.github.io/autora-experimentalist-poppernet/
Requires-Dist: autora-core
Requires-Dist: scikit-learn
Requires-Dist: torch
Provides-Extra: dev
Requires-Dist: autora-core[dev] ; extra == 'dev'
